{
    "classes": [
        "CODE"
    ],
    "annotations": [
        [
            "Use code EXCLUSIVE2023 on Postmates for $15 off, $30 minimum. https://t.co/KZYx9WRPUc",
            {
                "entities": [
                    [
                        9,
                        22,
                        "CODE"
                    ]
                ]
            }
        ],
        [
            "Use code AFW25 on Postmates for $25 off, no minimum. Texas Only! Works for pickup! https://t.co/J5JlK3BnxB",
            {
                "entities": [
                    [
                        9,
                        14,
                        "CODE"
                    ]
                ]
            }
        ],
        [
            "POSTMATES FREE $25 OFF $25 ORDERS  Texas residents only!  Use promotional code “AFW25” https://t.co/kVV0Vj3XSS",
            {
                "entities": [
                    [
                        79,
                        86,
                        "CODE"
                    ]
                ]
            }
        ],
        [
            "$25 off $30 Postmates Code *only valid for Texas*  TACOS25 https://t.co/Eq4jbLq2y5",
            {
                "entities": [
                    [
                        51,
                        58,
                        "CODE"
                    ]
                ]
            }
        ],
        [
            "@Postmates_Help I have a promo code that used to be available now I can’t use why is this ??",
            {
                "entities": []
            }
        ],
        [
            "Shout outs to postmates!! Make sure you get your free meal if you’re at AfroTech—use code AfroTech23 at checkout! #AFROTECH23 https://t.co/iFjVmlCpRq",
            {
                "entities": [
                    [
                        115,
                        125,
                        "CODE"
                    ]
                ]
            }
        ],
        [
            "Use code AFROTECH23 on Postmates for $25 off, no minimum.   Texas Only! Works for pickup! https://t.co/VMdWw0R9ha",
            {
                "entities": [
                    [
                        9,
                        19,
                        "CODE"
                    ]
                ]
            }
        ],
        [
            "OOP! If you are in Austin for AfroTech, looks like Postmates got y’all wiyh a free meal with code AfroTech23",
            {
                "entities": [
                    [
                        98,
                        108,
                        "CODE"
                    ]
                ]
            }
        ],
        [
            "FREE POSTMATES AGAIN!  Don’t say I never gave you nothing. 🤝🏾 #Austin #SanAntonio https://t.co/XLNPTxlwQ4",
            {
                "entities": []
            }
        ],
        [
            "If you live in Texas, try code “EATUP” on Postmates https://t.co/M68AeY8nYP",
            {
                "entities": [
                    [
                        31,
                        38,
                        "CODE"
                    ]
                ]
            }
        ],
        [
            "$25 of Free Food from Postmates - TEXAS ONLY enter promo code TEXAS25 https://t.co/sgQ8RqKWYU",
            {
                "entities": [
                    [
                        62,
                        69,
                        "CODE"
                    ]
                ]
            }
        ],
        [
            "**POSTMATES $25 CODE FOR TX**   TEXAS25 https://t.co/JGtLjCYy9s",
            {
                "entities": [
                    [
                        32,
                        39,
                        "CODE"
                    ]
                ]
            }
        ],
        [
            "Get 70% off using Postmates promo code for October 2023 #postmates #postmatespromocode #postmatespromocodes #postmatespromocodes2023 #postmatescoupons #postmatesfreeshipping #postmatesdiscountcode #postmatescouponcode https://t.co/Gs9pj4PzJV",
            {
                "entities": []
            }
        ],
        [
            "Use code TEXAS25 on Postmates for $25 off, no minimum. Texas Only! Works for pickup! https://t.co/EBuwuq9Q1f",
            {
                "entities": [
                    [
                        9,
                        16,
                        "CODE"
                    ]
                ]
            }
        ],
        [
            "Use code TEXAS25 on Postmates for $25 off, no minimum. Texas Only! Works for pickup! https://t.co/dbKY1GTJPn",
            {
                "entities": [
                    [
                        9,
                        16,
                        "CODE"
                    ]
                ]
            }
        ],
        [
            "@SuperstarKota_ Fenna order mine w this  postmates code after work 😂🔥",
            {
                "entities": []
            }
        ],
        [
            "@fiveftsmol bf is forever postmates code isn’t 🥰 https://t.co/h40wtaw62A",
            {
                "entities": []
            }
        ],
        [
            "@Tracker_Deals Lmao I was on Postmates getting mad cause the code wasn’t going through 😂😂😭 Placed my order on Grubhub though thanks",
            {
                "entities": []
            }
        ],
        [
            "@ziddi_i @Postmates @Postmates_Help code ??",
            {
                "entities": []
            }
        ],
        [
            "@Postmates A discount code",
            {
                "entities": []
            }
        ],
        [
            "@howlinrays @Postmates @OffsetYRN I tried using the code today and got an error can I please get help? My account got frozen from promos on uber eats and I have proof from customer service that it was an error on their side. Now it's happening again but on postmates. I would like to actually use promos I receive.",
            {
                "entities": []
            }
        ],
        [
            "@Postmates  why give out a code that doesn’t work at any store? I tap “shop now” but it doesn’t give me a list of stores. Glitchy app :( https://t.co/nqPWnhhCUz",
            {
                "entities": []
            }
        ],
        [
            "Postmates: $20 Off $35 With Promo Code OFFSET https://t.co/kruf54jQD4 https://t.co/1NCJyUXcAw",
            {
                "entities": [
                    [
                        39,
                        45,
                        "CODE"
                    ]
                ]
            }
        ],
        [
            "#Postmates: $20 Off $35 With Promo Code **OFFSET** https://t.co/b89A0oDl5f",
            {
                "entities": [
                    [
                        40,
                        50,
                        "CODE"
                    ]
                ]
            }
        ],
        [
            "Postmates: $20 Off $35 With Promo Code OFFSET https://t.co/s4yXRRfWWa https://t.co/tpk3Hw0uub",
            {
                "entities": [
                    [
                        39,
                        45,
                        "CODE"
                    ]
                ]
            }
        ],
        [
            "$20 off $35 Postmates   code: OFFSET  #Postmates https://t.co/ubo2NhXUsy",
            {
                "entities": [
                    [
                        30,
                        36,
                        "CODE"
                    ]
                ]
            }
        ],
        [
            "When you finally find a Postmates promo code after you've already ordered food 😢",
            {
                "entities": []
            }
        ],
        [
            "Postmates App $20 Off $35  HURRY!  Apply  Promo Code: OFFSET",
            {
                "entities": [
                    [
                        54,
                        60,
                        "CODE"
                    ]
                ]
            }
        ],
        [
            "@EWatts78 \"OFFSET\" on Postmates for $20 off $35 purchase, code just dropped",
            {
                "entities": [
                    [
                        11,
                        17,
                        "CODE"
                    ]
                ]
            }
        ],
        [
            "@Postmates_Help HI! I just placed an order that seems to have disappeared automatically. I tried reordering , but my promo code doesn't apply anymore. Please look into it",
            {
                "entities": []
            }
        ],
        [
            "@Postmates \"OFFSET\" on Postmates for $20 off $35 purchase, code just dropped",
            {
                "entities": [
                    [
                        12,
                        18,
                        "CODE"
                    ]
                ]
            }
        ],
        [
            "@bheadreaper \"OFFSET\" on Postmates for $20 off $35 purchase, code just dropped",
            {
                "entities": [
                    [
                        14,
                        20,
                        "CODE"
                    ]
                ]
            }
        ],
        [
            "Code OFFSET   POSTMATES https://t.co/EotfQlgHqT",
            {
                "entities": [
                    [
                        5,
                        11,
                        "CODE"
                    ]
                ]
            }
        ],
        [
            "@alanarexic \"OFFSET\" on Postmates for $20 off $35 purchase, code just dropped",
            {
                "entities": [
                    [
                        13,
                        19,
                        "CODE"
                    ]
                ]
            }
        ],
        [
            "Postmates $20 off $30   Use code OFFSET https://t.co/L6rklg2ZJr",
            {
                "entities": [
                    [
                        33,
                        39,
                        "CODE"
                    ]
                ]
            }
        ],
        [
            "Postmates $20 off $35 (combine w local bogo offers)   Code - OFFSET https://t.co/YW6G7EXa05",
            {
                "entities": [
                    [
                        61,
                        67,
                        "CODE"
                    ]
                ]
            }
        ],
        [
            "Postmates $20 off $35  Promo code: OFFSET",
            {
                "entities": [
                    [
                        35,
                        41,
                        "CODE"
                    ]
                ]
            }
        ],
        [
            "Use code OFFSET on Postmates for $20 off $35 minimum. https://t.co/aYyfyK1PY4",
            {
                "entities": [
                    [
                        9,
                        15,
                        "CODE"
                    ]
                ]
            }
        ],
        [
            "Postmates $20 off $35  Promo code: OFFSET",
            {
                "entities": [
                    [
                        35,
                        41,
                        "CODE"
                    ]
                ]
            }
        ],
        [
            "Postmates $20 off $35 order. Add to your account now before it is gone, use any time enter code OFFSET https://t.co/P6V3xXewQZ",
            {
                "entities": [
                    [
                        96,
                        102,
                        "CODE"
                    ]
                ]
            }
        ],
        [
            "@Postmates Depends on what code you give me 🤔😏",
            {
                "entities": []
            }
        ],
        [
            "Get 70% off using Postmates promo code for October 2023 #postmates #postmatespromocode #postmatespromocodes #postmatespromocodes2023 #postmatescoupons #postmatesfreeshipping #postmatesdiscountcode #postmatescouponcode https://t.co/Gs9pj4PzJV",
            {
                "entities": []
            }
        ],
        [
            "Use code CALEB on Postmates for $13 off, $30 minimum. Los Angeles only! https://t.co/didkp2jIXY",
            {
                "entities": [
                    [
                        9,
                        14,
                        "CODE"
                    ]
                ]
            }
        ],
        [
            "POSTMATES $25 off! Dallas Texas ONLY!  Promo code: 254SD https://t.co/l8thJyER59",
            {
                "entities": [
                    [
                        51,
                        56,
                        "CODE"
                    ]
                ]
            }
        ],
        [
            "@Postmates_Help   I ordered using a promo code that was given to me by your company and tried to order multiple times but every time it goes back saying the promo cannot be applied even though it’s stores you recommend for it.",
            {
                "entities": []
            }
        ],
        [
            "Use code 254SD on Postmates for $25 off, no minimum. Dallas only! https://t.co/vCQi1OeFtL",
            {
                "entities": [
                    [
                        9,
                        14,
                        "CODE"
                    ]
                ]
            }
        ],
        [
            "@Postmates_Help I used a promo code that was available and i have screenshots of it taking the money off, but it charged me full price",
            {
                "entities": []
            }
        ],
        [
            "@Postmates_Help the LA30 code is not working for any restaurant and it’s crazy",
            {
                "entities": [
                    [
                        20,
                        24,
                        "CODE"
                    ]
                ]
            }
        ],
        [
            "@Postmates_Help my code LA30 worked two days ago but no longer today. Pls assist.",
            {
                "entities": [
                    [
                        24,
                        28,
                        "CODE"
                    ]
                ]
            }
        ],
        [
            "@Postmates_Help help my promo code isn’t applying",
            {
                "entities": []
            }
        ],
        [
            "@Postmates_Help  Your customer service is horrible and slow. How can I apply a promo code and once the order process, the code does not apply. You refuse to cancel order or refund the promo amount. Once ask for a supervisor, I was refused and the chat was ended. The worst reps!",
            {
                "entities": []
            }
        ],
        [
            "$20 Off $40 via Postmates - Las Vegas Only  - For 2 Orders - Code: 20VEGAS https://t.co/Ch16Vr104Y",
            {
                "entities": [
                    [
                        67,
                        74,
                        "CODE"
                    ]
                ]
            }
        ],
        [
            "@visegrad24 All of their parents drive Postmates and code poorly in Python3",
            {
                "entities": []
            }
        ],
        [
            "Another poor customer service experience from @UberEats and @Postmates. Can’t apply my promo code to my order. Switched to @DoorDash right away. Great “promo” job here. https://t.co/qUj5PVVzCk",
            {
                "entities": []
            }
        ],
        [
            "bro @Postmates scammed me fr, i was applying a promo code and it showed that it was $25 off and then when i confirmed the order and checked out it charged me the full total 🥲😭",
            {
                "entities": []
            }
        ],
        [
            "Get 70% off using Postmates promo code for October 2023 #postmates #postmatespromocode #postmatespromocodes #postmatespromocodes2023 #postmatescoupons #postmatesfreeshipping #postmatesdiscountcode #postmatescouponcode https://t.co/Gs9pj4PzJV",
            {
                "entities": []
            }
        ],
        [
            "@Postmates_Help I ordered using a promo code that was given to me by your company and tried to order multiple times but every time it kicked back saying the promo cannot be applied even though it’s stores you recommend for it. I pay for Uber One as well but it seems that I should cancel it.",
            {
                "entities": []
            }
        ],
        [
            "Code: NEWMATES  Postmates $20 off $25 code working again 💪💪 https://t.co/NZHxpFETOm",
            {
                "entities": [
                    [
                        6,
                        14,
                        "CODE"
                    ]
                ]
            }
        ],
        [
            "Why isn’t my promo code working?? @Postmates https://t.co/j3OnOl4hAD",
            {
                "entities": []
            }
        ],
        [
            "CODE: MATCH25   $25 off postmates https://t.co/BAZN6LTSU6",
            {
                "entities": [
                    [
                        6,
                        13,
                        "CODE"
                    ]
                ]
            }
        ],
        [
            "POSTMATES $25 off  Promo code: MATCH25 https://t.co/ov5ynIeuLZ",
            {
                "entities": [
                    [
                        31,
                        38,
                        "CODE"
                    ]
                ]
            }
        ],
        [
            "Use code MATCH25 for $25 off, no minimum on Postmates! Select cities only, see photo. https://t.co/jlY17x8fhm",
            {
                "entities": [
                    [
                        9,
                        16,
                        "CODE"
                    ]
                ]
            }
        ],
        [
            "Use code EATUP on Postmates for $12 off, $35 minimum! https://t.co/k4fLloX9IK",
            {
                "entities": [
                    [
                        9,
                        14,
                        "CODE"
                    ]
                ]
            }
        ],
        [
            "@Postmates My $30 of $35 code LA30 isn’t working and I haven’t used it 3 times",
            {
                "entities": [
                    [
                        30,
                        34,
                        "CODE"
                    ]
                ]
            }
        ],
        [
            "@Postmates_Help hello, having an issues with $30 of $35 LA30 code. Have used it twice and trying to order a 3rd and keeps giving an error",
            {
                "entities": [
                    [
                        56,
                        60,
                        "CODE"
                    ]
                ]
            }
        ],
        [
            "Get 70% off using Postmates promo code for October 2023 #postmates #postmatespromocode #postmatespromocodes #postmatespromocodes2023 #postmatescoupons #postmatesfreeshipping #postmatesdiscountcode #postmatescouponcode https://t.co/Gs9pj4PzJV",
            {
                "entities": []
            }
        ],
        [
            "@Postmates_Help Whenever I try to add a promotion code, it says “Unfortunately, your account is ineligible…” However, my friend’s account was able to redeem the same promotion code without any issues. We’ve both ordered at least once on our accounts, so no differences there.",
            {
                "entities": []
            }
        ],
        [
            "Use code BOULDERTHON25 and BOULDERTHON30 for 25% and 30% off Uber Eats and Postmates! https://t.co/V8wMi4CwvC",
            {
                "entities": [
                    [
                        9,
                        22,
                        "CODE"
                    ],
                    [
                        27,
                        40,
                        "CODE"
                    ]
                ]
            }
        ],
        [
            "@Postmates_Help it keeps giving me a error code everytime i try to place a order",
            {
                "entities": []
            }
        ],
        [
            "Gets a promo code for $30 off $35 on Postmates. So I should be spending like $5 plus tax. Total comes out to $28.66 with $30 discount before tip. Make it make sense.",
            {
                "entities": []
            }
        ],
        [
            "@Postmates so you guys disabled my discount code and then refused to let me cancel my order? then on top of that restricted my account and took away my only other $15 off code?  Now I'm paying the FULL amount without the code that YOU put in and advertised to me  wtf man",
            {
                "entities": []
            }
        ],
        [
            "@Postmates Code please",
            {
                "entities": []
            }
        ],
        [
            "@Postmates_Help sent you a Dm as I’m having problems with promo code applications",
            {
                "entities": []
            }
        ],
        [
            "@Postmates_Help why does my promo code not apply to my orders on food? Also what is your contact number I’m extremely frustrated",
            {
                "entities": []
            }
        ],
        [
            "@Postmates_Help Code please",
            {
                "entities": []
            }
        ],
        [
            "POSTMATES $25 off!! Texas only!  Promo code: TACOS25 https://t.co/mKueDOADjb",
            {
                "entities": [
                    [
                        45,
                        52,
                        "CODE"
                    ]
                ]
            }
        ],
        [
            "@Postmates_Help Code please",
            {
                "entities": []
            }
        ],
        [
            "$25 off Postmates If youre in the Texas area Use code TACOS25 https://t.co/a4Ltrw7416",
            {
                "entities": [
                    [
                        54,
                        61,
                        "CODE"
                    ]
                ]
            }
        ],
        [
            "$25 off Postmates If youre in the Texas area Use code TACOS25",
            {
                "entities": [
                    [
                        54,
                        61,
                        "CODE"
                    ]
                ]
            }
        ],
        [
            "Postmates $25 OFF $30 (Select Locations)  Code TACOS25 https://t.co/PjgXK8TLdT",
            {
                "entities": [
                    [
                        47,
                        54,
                        "CODE"
                    ]
                ]
            }
        ],
        [
            "@Amandakp00 @Postmates_Help haha so umm what code was it 😇",
            {
                "entities": []
            }
        ],
        [
            "Hidden members FEASTED off free Postmates this weekend 😋   Did you manage to catch the code? 👇 💭 https://t.co/LoRP8fL7kQ",
            {
                "entities": []
            }
        ],
        [
            "@Postmates @Postmates_Help I was sent a code ‘FOODNOW20’ and it is not working. Why?",
            {
                "entities": [
                    [
                        45,
                        56,
                        "CODE"
                    ]
                ]
            }
        ],
        [
            "Not my usual content but too good not to post. For anyone who uses @Postmates use code BESTOFNASH for $30 off $35. https://t.co/azCuUVV7ay",
            {
                "entities": [
                    [
                        87,
                        97,
                        "CODE"
                    ]
                ]
            }
        ],
        [
            "[YMMV] #Postmates: $30 Off $35 With Promo Code **BESTOFNASH** https://t.co/bWIq18iMCn",
            {
                "entities": [
                    [
                        47,
                        61,
                        "CODE"
                    ]
                ]
            }
        ],
        [
            "Postmates: $30 Off $35 With Promo Code BESTOFNASH https://t.co/BW0VvO09vA https://t.co/dFolFM9Yvr",
            {
                "entities": [
                    [
                        39,
                        49,
                        "CODE"
                    ]
                ]
            }
        ],
        [
            "@Amandakp00 We're sorry to hear that your promo code did not apply to your order. Please send us a DM with the phone number and email address associated with your account along with the order details, so that we can assist you further. Looking forward to your response. https://t.co/s3LZHS5jNs",
            {
                "entities": []
            }
        ],
        [
            "FREE POSTMATES ORDERS 😋  Use code BESTOFNASH",
            {
                "entities": [
                    [
                        35,
                        45,
                        "CODE"
                    ]
                ]
            }
        ],
        [
            "@nftpowerranking If you use Postmates, try code: LA30",
            {
                "entities": [
                    [
                        49,
                        53,
                        "CODE"
                    ]
                ]
            }
        ],
        [
            "POSTMATES CODE $30 off a $35 order  Select accounts    Promo code: BESTOFNASH https://t.co/0OnFprfwzc",
            {
                "entities": [
                    [
                        67,
                        77,
                        "CODE"
                    ]
                ]
            }
        ],
        [
            "Postmates Promo Codes: $10 Off $35 with Code THATNEWNEW https://t.co/ovzYi1GvmW",
            {
                "entities": [
                    [
                        45,
                        55,
                        "CODE"
                    ]
                ]
            }
        ],
        [
            "Postmates code LA30   GO",
            {
                "entities": [
                    [
                        15,
                        19,
                        "CODE"
                    ]
                ]
            }
        ],
        [
            "use code A&amp;MHOME on postmates for 25$ off ( TEXAS ONLY )",
            {
                "entities": []
            }
        ],
        [
            "$10 off a order total of $35 on Postmates  Promo Code: THATNEWNEW  EAT UP! 😋",
            {
                "entities": [
                    [
                        55,
                        65,
                        "CODE"
                    ]
                ]
            }
        ],
        [
            "$10 off a order total of $35 on Postmates  Promo Code: THATNEWNEW  EAT UP! 😋",
            {
                "entities": [
                    [
                        55,
                        65,
                        "CODE"
                    ]
                ]
            }
        ],
        [
            "Use code THATNEWNEW for $10 off, $35 minimum for Postmates code https://t.co/riKZodCbwY",
            {
                "entities": [
                    [
                        9,
                        19,
                        "CODE"
                    ]
                ]
            }
        ],
        [
            "just ordered the most big back meal on postmates because i found a 35$ off code on tiktok https://t.co/FmMak1ELfV",
            {
                "entities": []
            }
        ],
        [
            "Postmates Use code $25 Off,  min $35+    AFFEATS25OCT",
            {
                "entities": [
                    [
                        41,
                        53,
                        "CODE"
                    ]
                ]
            }
        ],
        [
            "@Postmates_Help I have a promo code In my account that keeps getting taken off after I pay and sends me back to checkout. Can you apply it for me",
            {
                "entities": []
            }
        ],
        [
            "Give it a shot. If it doesn't work, keep spamming.    Postmates code!   NEWMATES ($20 off, $25 min)    BOBA20 ($20 off, $25 min)    SUSHI20  ($20 off, $25 min)    BESTOFNASH ($30 off, $35 min)   DUMPLING20 ($20 off, $25 min)    DONUT20 ($20 off, $25 min)",
            {
                "entities": [
                    [
                        72,
                        80,
                        "CODE"
                    ],
                    [
                        103,
                        109,
                        "CODE"
                    ],
                    [
                        132,
                        139,
                        "CODE"
                    ],
                    [
                        163,
                        173,
                        "CODE"
                    ],
                    [
                        195,
                        205,
                        "CODE"
                    ],
                    [
                        228,
                        235,
                        "CODE"
                    ]
                ]
            }
        ],
        [
            "Use code SUSHI20 on Postmates for $20 off, $25 minimum!  Join our discord today for quick notifications! https://t.co/jdUAXZn4r6",
            {
                "entities": [
                    [
                        9,
                        16,
                        "CODE"
                    ]
                ]
            }
        ],
        [
            "Get 70% off using Postmates promo code for October 2023 #postmates #postmatespromocode #postmatespromocodes #postmatespromocodes2023 #postmatescoupons #postmatesfreeshipping #postmatesdiscountcode #postmatescouponcode https://t.co/Gs9pj4PzJV",
            {
                "entities": []
            }
        ],
        [
            "WHOA!! 😱 SUPER HOT POSTMATES DEAL!!  For a very limited time, score $30 off of a $35.00+ order with Postmates! Use code LA30 to get the deal! https://t.co/emTmqi6McY",
            {
                "entities": []
            }
        ],
        [
            "Postmates: $30 Off $35 With Promo Code LA30 https://t.co/jhX42OWj9g https://t.co/E1qLZAehqR",
            {
                "entities": [
                    [
                        39,
                        43,
                        "CODE"
                    ]
                ]
            }
        ],
        [
            "POSTMATES $25 OFF COUPON AGAIN!  USE CODE A&amp;MHOME   Only for TX https://t.co/eDKzonu4nt",
            {
                "entities": []
            }
        ],
        [
            "Postmates $25 OFF - Texas Only   Code: A&amp;MHOME https://t.co/F3jCRVbQvc",
            {
                "entities": []
            }
        ],
        [
            "Postmates code! Worked for me! https://t.co/dMqcAH8HkZ",
            {
                "entities": []
            }
        ],
        [
            "POSTMATES $25 off!! Texas only!  Promo code: A&amp;MHOME https://t.co/pvs8YentzS",
            {
                "entities": []
            }
        ],
        [
            "POSTMATES has a deal spend $35 get $30 off with the code LA30 I just got 2 chipotle bowls,  a kids meal, a side of queso, and a drink for $22 you’re welcome https://t.co/G8l3D12FsX",
            {
                "entities": [
                    [
                        57,
                        61,
                        "CODE"
                    ]
                ]
            }
        ],
        [
            "@Postmates_Help @Postmates I used the promo code on the checkout page and it succeeded . When I looked at the confirmation page, it returned to the original price. Instead of letting me know the promo didn’t apply, they tricked me by changing the price without notice. https://t.co/esrW1a8p0Q",
            {
                "entities": []
            }
        ],
        [
            "5€ sur ta première commande avec ce code Uber eats profitez https://t.co/HBmU3peddg",
            {
                "entities": []
            }
        ],
        [
            "Falls ihr auch einen 20€ Gutschein wollt und noch kein Uber Eats habt nutzt meinen Code: eats-oqxetdj9rr",
            {
                "entities": []
            }
        ],
        [
            "@ubereats_uk #uber Does that say the code should work for 5 orders ? So I used it on one order and now there aren’t any participating restaurants funnily for me to use it another 4 times ? 🤥 https://t.co/iJVPgTR20W",
            {
                "entities": []
            }
        ],
        [
            "Uber Eats promo code #Free #UberEats",
            {
                "entities": []
            }
        ],
        [
            "Uber Eats promo code free Hungry? Get $15 off your first Uber Eats order of $20 or more. Terms apply. Use my code at checkout: eats-georgew59fue   https://t.co/d89lDbQjv3",
            {
                "entities": []
            }
        ],
        [
            "is there a doordash or uber eats discount code plsss guys",
            {
                "entities": []
            }
        ],
        [
            "Uber Eats #Free promo code",
            {
                "entities": []
            }
        ],
        [
            "Ceux qui recherche un code Uber eats ✨ voici sur ta première commande https://t.co/enFvHvcV9i",
            {
                "entities": []
            }
        ],
        [
            "eats-ko1wevd34x  ✨Code Uber eats de 5€ sur ta première commande ✨✨✨",
            {
                "entities": []
            }
        ],
        [
            "@UberEats there’s a bug right now on your iOS app where if u use the usual 40% off 40$ coupon and combine it with the restaurant buy 1 get 1 offers, promo code does not work. Doing the same thing from the same store on my brother’s android works 🙊🤷🏼",
            {
                "entities": []
            }
        ],
        [
            "Uber Eats ##NFL #UberEats promo code",
            {
                "entities": []
            }
        ],
        [
            "@ubereats_uk driver just pulled up I gave him the code. He gives me the wrong order, we went through all his deliveries together and none of them were mine. I asked if he can flag it as an issue whilst I was connecting to live chat when suddenly it closed and he just drove off?",
            {
                "entities": []
            }
        ],
        [
            "eats-9oig0masim utilise mon code Uber Eats svp..",
            {
                "entities": []
            }
        ],
        [
            "@ubereats_uk Hi, when I get a discount code through email the restaurants I'm offered are miles away from us so cannot order unless we want cold food. Why is this? My address is set correctly in my account.",
            {
                "entities": []
            }
        ],
        [
            "@ubereats_fr sinon uber on paye un abonnement mais on a jamais de code promo chez vous ?????",
            {
                "entities": []
            }
        ],
        [
            "Un code promo uber eats pitié 😭😭😭",
            {
                "entities": []
            }
        ],
        [
            "Free Uber Eats promo code #UberEats #Free",
            {
                "entities": []
            }
        ],
        [
            "Uber Eats promo code free Hungry? Get $15 off your first Uber Eats order of $20 or more. Terms apply. Use my code at checkout: eats-georgew59fue   https://t.co/d89lDbQjv3",
            {
                "entities": []
            }
        ],
        [
            "Code promo uber eats: eats-resjjufe3h",
            {
                "entities": []
            }
        ],
        [
            "@MostlyMonkey I need advice bro. I've got a bsc in accounting from cuny and want to make 50k. Right now I'm learning to code. Really want to break out of the 30-40k Range.   40 female NYC, most of my friends are FedEx, Amazon, UberEats, workers. No solid blue collar man for me to marry.",
            {
                "entities": []
            }
        ],
        [
            "Uber Eats #UberEats #promo promo code free #Free $$$",
            {
                "entities": []
            }
        ],
        [
            "@UberEats i cant seem to use this local promotional code even though I am located in the LA area? The promotional code refuses to apply to my cart. https://t.co/xOQcKWoYTM",
            {
                "entities": []
            }
        ],
        [
            "@ThatNiggaHemi Cheat code : they probably raised prices cuz if you order on uber eats its $5 off of $10",
            {
                "entities": []
            }
        ],
        [
            "@UberEats the support account now has posts in russian, so i'm writing to y'all. i have a promo code for 50% off that does not expire until *tomorrow* (5th of nov.) but when i enter it, it says it has expired.  can you help?",
            {
                "entities": []
            }
        ],
        [
            "#free Uber Eats promo code $",
            {
                "entities": []
            }
        ],
        [
            "Uber Eats promo code free Hungry? Get $15 off your first Uber Eats order of $20 or more. Terms apply. Use my code at checkout: eats-georgew59fue   https://t.co/d89lDbQjv3",
            {
                "entities": []
            }
        ],
        [
            "Uber eats  Hungrig? Spare 20 $ bei deiner ersten Uber Eats Bestellung im Wert von mindestens 25 $. Es gelten die AGB. Meinen Code beim Bezahlen verwenden: eats-kthemibm1w   https://t.co/YzXi4IgWJP #uber #ubereats #food #fooddelivery #save",
            {
                "entities": []
            }
        ],
        [
            "5€ sur ta première commande avec ce code Uber eats... https://t.co/lkZtKVUESJ",
            {
                "entities": []
            }
        ],
        [
            "J'ai commandé Uber eats jarrive ya un gars avec mon livreur et il veut me piquer ma commande !!! Heureusement yavait un code a donner au livreur je m'approche et la le gars me dit \"tas de la chance j'allais piquer ta commande\" en partant  ALLOOO 😭😭😭😭",
            {
                "entities": []
            }
        ],
        [
            "I’m drunk and I’m getting Uber eats for the second time in my life and my anxiety is through the roof. I gotta give this persons a code?",
            {
                "entities": []
            }
        ],
        [
            "@tjsjbackup UBER EATS PROMO CODE IN HIDDEN",
            {
                "entities": []
            }
        ],
        [
            "eats-kt79h9 use this code at uber eats",
            {
                "entities": []
            }
        ],
        [
            "Ubereats ils font plus aucune réduc ou c’est moi ? Déjà qu’ils nous volent ils pourraient au moins lâcher un petit code promo",
            {
                "entities": []
            }
        ],
        [
            "@ubereats_uk @Uber_Support   One of your drivers faked having my food today in cramlington to get the PIN code then drove off. I rang the restaurant to be told he never collected my food.   Now I’m being called a liar on webchat because he had my pin? Sort this out",
            {
                "entities": []
            }
        ],
        [
            "@ubereats_uk @UberEats   One of your drivers faked having my food today in cramlington to get the PIN code then drove off. I rang the restaurant to be told he never collected my food.   Now I’m being called a liar on webchat because he had my pin? Sort this out",
            {
                "entities": []
            }
        ],
        [
            "5€ sur ta première commande avec ce code Uber eats https://t.co/u5fvTrlqvg",
            {
                "entities": []
            }
        ],
        [
            "5€ sur ta première commande avec ce code Uber eats eats-ko1wevd34x",
            {
                "entities": []
            }
        ],
        [
            "Uber Eats #UberEats #Free promo code $$$",
            {
                "entities": []
            }
        ],
        [
            "Uber Eats promo code free Hungry? Get $15 off your first Uber Eats order of $20 or more. Terms apply. Use my code at checkout: eats-georgew59fue   https://t.co/d89lDbQjv3",
            {
                "entities": []
            }
        ],
        [
            "Code promo uber eats de -5€ sur votre première commande d’un montant de 15€: eats-14dkby6c0k",
            {
                "entities": []
            }
        ],
        [
            "Uber eats ils donnent plus de code promo pour la 1ere commande ?",
            {
                "entities": []
            }
        ],
        [
            "Uber Eats free promo code #UberEats #Free",
            {
                "entities": []
            }
        ],
        [
            "Sie müssen Essen bestellen? Erhalte 10 € Rabatt auf deine ersten 2 Bestellungen im Wert von 20 € oder mehr, wenn du über Uber Eats bestellst. Es gelten die allgemeinen Geschäftsbedingungen. Verwende meinen Code an der Kasse: eats-hlu0qu   https://t.co/ngmomDcYbc #ubereats：）",
            {
                "entities": []
            }
        ],
        [
            "🍗🍔🍟🍜$5 OFF ORDER #skipthedishes: https://t.co/bS87DAgXzx  🌮🌯🍿🍕$15 OFF 3 ORDERS #ubereats code:  eats-0ib6vn29te  ❄️🇨🇦CANADA ONLY🇨🇦❄️ #Ad #Viral #SmackDown #OPLive #RockHall2023 #FortniteOG #GenV Marchand #NHLBruins #coupon #food https://t.co/lYUbAMH1sh",
            {
                "entities": []
            }
        ],
        [
            "Uber Eats #UberEats promo code #free #FreebieFriday",
            {
                "entities": []
            }
        ],
        [
            "Uber Eats promo code free Hungry? Get $15 off your first Uber Eats order of $20 or more. Terms apply. Use my code at checkout: eats-georgew59fue   https://t.co/d89lDbQjv3",
            {
                "entities": []
            }
        ],
        [
            "qq veut un code uber eats 2x10€ ?",
            {
                "entities": []
            }
        ],
        [
            "Salem vous avez un code Uber eats -15",
            {
                "entities": []
            }
        ],
        [
            "Thank you Juan and Isabel for cashing in on my Uber Eats promo code. You’re the real MVP!!   How do you know you live in #NJ ???  👀👀 😋🤤  🔥Get $20 off your UberEats order. Use my code at checkout  eats-richp904ue   https://t.co/5Yr547scaz🔥 https://t.co/aXI8GByZgi",
            {
                "entities": []
            }
        ],
        [
            "That 50% off Uber Eats code is 🤌🏾🤌🏾",
            {
                "entities": []
            }
        ],
        [
            "Uber Eats #UberEats promo code free",
            {
                "entities": []
            }
        ],
        [
            "i need a uber eats or doordash promo code lmaoo",
            {
                "entities": []
            }
        ],
        [
            "Uber Eats code free",
            {
                "entities": []
            }
        ],
        [
            "Qui a un code promo uber eats urgent la chienneté ?",
            {
                "entities": []
            }
        ],
        [
            "hey everyone! if you use my uber eats promo code or my doordash promo code you’ll save $20 (and it was also save me money, you’ll really be doing me a solid here)   uber eats code: eats-brookep5600ui link to doordash: https://t.co/BiIcE0OtOz https://t.co/EIuq3zhrQy",
            {
                "entities": []
            }
        ],
        [
            "I'm trying to fast and a friend of mine sent me an Uber eats discount code. The fuck?!",
            {
                "entities": []
            }
        ],
        [
            "and was there any reason to deselect the restaurant Uber Eats selected because of a code wouldn’t be much of a report on the state of the national hobby if had and why would such games be significant to me anyhow doesn’t make any difference because interest codes are only as powerful as your belief in the codes there isn’t much road left on your games and are very repetitive presumably is a comment akin to the ideas in tar  about suggesting repetition and asserting your games and assertions about how identities operate or define and the meanings to identities which you ascribe which the audience is then meant to believe or follow or believe and follow while you choose not to tell the truth about how actually all aspects are and the truth of linear time as opposed to your time games and how the messing around of perception about time and messing around has affected those aspects which out of your games are subject to linear time but you want be most subject to your games and you and your warping of perceptions and by programming the populace with cues you can be fishing around for affecting people situations (no don’t know anything about how you operate you’re still such a mystery no wonder cannot be bothered to be worried about codes only the bozos following the codes which are the chaos otherwise is only words on a screen and food at the doorstep)",
            {
                "entities": []
            }
        ],
        [
            "@UberUKsupport @UberEats my coupon code still isn’t working?? Why send it me if I can’t order !!",
            {
                "entities": []
            }
        ],
        [
            "Nice of @ubereats_uk to give me a 50% off discount code, oh wait no because it can’t be used in any place near me! Completely pointless",
            {
                "entities": []
            }
        ],
        [
            "Free candy to the 805 area code tomorrow during my uber eats deliveries",
            {
                "entities": []
            }
        ],
        [
            "@UberEats Please gimme a promo code so I can buy this food",
            {
                "entities": []
            }
        ],
        [
            "BOGO free deals on Uber eats are where it’s at! Especially if you got a promo code on top of it. I got $90 worth of food for $35.",
            {
                "entities": []
            }
        ],
        [
            "Ubereats sent me a code that only works at specific restaurants, meanwhile Nothing on that list is what I want 😒😒😒",
            {
                "entities": []
            }
        ],
        [
            "use my Uber eats code get $20off please guys please i make $10 an hour help a sister out🙏🏾🙏🏾🙏🏾 eats-katied17735ue https://t.co/jCItT0zLjk",
            {
                "entities": []
            }
        ],
        [
            "Qui a un code #UberEats",
            {
                "entities": []
            }
        ],
        [
            "5€ sur ta première commande avec ce code Uber eats https://t.co/o15WFcUid0",
            {
                "entities": []
            }
        ],
        [
            "@UberEats Does that code work on Epstein Island? https://t.co/OIKwuSikFl",
            {
                "entities": []
            }
        ],
        [
            "@ubereats_uk what’s the point in sending me a 40% off code, when there’s nothing on the app that says where I can use it, and seemingly none of the places I pick accept it. No list anywhere.  But it’s fine I’ll use just eat or deliveroo since they can run a promotion. Wank.",
            {
                "entities": []
            }
        ],
        [
            "Code promo uber eats pour manger GRATUIT PITIÉ GENRE J’AI TEOP ENVIE LÀ",
            {
                "entities": []
            }
        ],
        [
            "Je déteste quand uber eats me donne un code à donner au livreur. Ça veut dire que je vais devoir parler à un être humain et c'est compliqué",
            {
                "entities": []
            }
        ],
        [
            "@UberEats just wanted to understand why promo code UKEAT50 is not working on my account? Whereas I am seeing the same working for everyone else. Could you please check.",
            {
                "entities": [
                    [
                        51,
                        58,
                        "CODE"
                    ]
                ]
            }
        ],
        [
            "Code promo Uber eats (10€ offert sur vos deux premières commandes)  welcomefr6j9lnz  #UberEats  @CodepromoUbere3",
            {
                "entities": []
            }
        ],
        [
            "@UberEats gimmie a break with the promo codes for essentials how about a promo code for actual food orders?   Sincerely,  A human too tired to feed themselves after multiple visits to the hospital to see their sick mom",
            {
                "entities": []
            }
        ],
        [
            "@synergistically @UberEats Leave at my door. I provided the gate code too. Literally everyone else gets this right, including other orders from today!",
            {
                "entities": []
            }
        ],
        [
            "@UberEats I used todays horror code and one of my discounted items was cancelled. The other was charged full price. I’ve now spoken with 2 agents who couldn’t help me. This is such trash.",
            {
                "entities": []
            }
        ],
        [
            "Code parrainage sushi shop : PRB120H 5€ offert sur votre première commande  #sushi #sushishop #UberEats #justeat #deliveroo #japonais #sashimi #maki  #baguette #saucesoja #gingembre #wasabi",
            {
                "entities": [
                    [
                        29,
                        36,
                        "CODE"
                    ]
                ]
            }
        ],
        [
            "Hungrig? Spare 10 € bei deinen ersten 2 Uber Eats Bestellungen von mindestens 20 €. Es gelten die AGB. Meinen Code beim Bezahlen verwenden: eats-wfop5dpm19   https://t.co/MmChI7Kqru",
            {
                "entities": []
            }
        ],
        [
            "mein leben wäre besser wenn wir ubereats hier hätten",
            {
                "entities": []
            }
        ],
        [
            "@ubereats_uk hi, I had a 50% off discount code, but you removed it from my account yesterday, what's going on?",
            {
                "entities": []
            }
        ],
        [
            "@UberEats The code isn’t working at check out. Waited at least 25 minutes",
            {
                "entities": []
            }
        ],
        [
            "Why tf would Uber eats give me a promo code &amp; then say it can’t be applied because it’s not valid anymore https://t.co/wWiBznaF8n",
            {
                "entities": []
            }
        ],
        [
            "@UberEats Le code marche pas",
            {
                "entities": []
            }
        ],
        [
            "Uber eats is so shiesty. Why they take away my promo code as I pay and charge me full price. @UberEats y’all are EMBEZZLING",
            {
                "entities": []
            }
        ],
        [
            "@UberEats Used the horror code and the candy was replaced and was charged full price.  now customer service won’t help",
            {
                "entities": []
            }
        ],
        [
            "@DamienRieu @ubereats_fr @Deliveroo_FR Il n’y a pas que là ; je me fais livrer mes courses alimentaires (grandes enseignes) et le nombre de livreurs parlant mal, voire peu, le français, ne cesse de grandir ; quand je leur donne le code de vérification, bcp réfléchissent avant de le taper sur leur tel",
            {
                "entities": []
            }
        ],
        [
            "What is the point in having a promo code that says you can use it 5 times for it to disappear ? Then a promo code that tells you you can’t use it in your area ? @ubereats_uk madness",
            {
                "entities": []
            }
        ],
        [
            "@ubereats_uk hi I’ve DM’d about my code not working 😭",
            {
                "entities": []
            }
        ],
        [
            "🍭🍫🍬🍦$5 OFF ORDER #skipthedishes: https://t.co/bS87DAgXzx  🍿🍕🍔🍟$15 OFF 3 ORDERS #ubereats code:  eats-0ib6vn29te  👻🎃🇨🇦CANADA ONLY🇨🇦👻🎃#Ad #Viral Halloween #trickortreat #Christmas #WWENXT #Canucks Leafs #UltraFirstGoal #GoAndTakeIt #DWTS #food #November #NovemberWish https://t.co/ZuNWFjQ3I8",
            {
                "entities": []
            }
        ],
        [
            "@UberEats my 50%off code isn’t working 😭",
            {
                "entities": []
            }
        ],
        [
            "@fatstevebuscemi Because I'm able to just leave the house to buy things, the only time I ever used anything like that was when I was profoundly unemployed and had a $20 Uber Eats coupon code and I just tipped the rest of my balance, then deleted my account.",
            {
                "entities": []
            }
        ],
        [
            "@UberEats This code is not working for me",
            {
                "entities": []
            }
        ],
        [
            "Use code IMYOURFRIENDTOTHEEND on Uber Eats for 60% off candy, halloween decor, or costumes! Codes drop everyday until October 31. https://t.co/hg9o7XHGWn https://t.co/61tJbZYODG",
            {
                "entities": [
                    [
                        9,
                        29,
                        "CODE"
                    ]
                ]
            }
        ],
        [
            "Uber Eats Code :  IWANTTOPLAYAGAME https://t.co/yH7aC5fhoy",
            {
                "entities": [
                    [
                        18,
                        34,
                        "CODE"
                    ]
                ]
            }
        ],
        [
            "@UberEats Please give me a promo code 🥺",
            {
                "entities": []
            }
        ],
        [
            "Use my uber eats referral code , though.  eats-y5su1h1gv2",
            {
                "entities": []
            }
        ],
        [
            "Quelqu’un aurait un code uber eats svp ?",
            {
                "entities": []
            }
        ],
        [
            "Allez vous abonner juste les 500 svp Jfait gagne 2 code promo nike 30% et 2 code promo Uber eats wallah #DonBelle #BallonDor #KGO https://t.co/PNMdwPqwCX",
            {
                "entities": []
            }
        ],
        [
            "me n my mum ordered kfc tonight not knowing they ask for a PIN code , the guy asks for this and my mum said 2 mins shuts the door and comes back wae a safety pin he went no no a PIN code”😭😂😂😂 stop it  @kfc  @UberEats  #kfc #ubereats",
            {
                "entities": []
            }
        ],
        [
            "@UberEats hi Uber eats how do I turn off the PIN code for order drop offs. I hate this feature and some people don’t just have it come to the front door no pin needed helped",
            {
                "entities": []
            }
        ],
        [
            "Code promo uber eats de -5€ sur votre première commande d’un montant de 15€: eats-14dkby6c0k",
            {
                "entities": []
            }
        ],
        [
            "@ubereats_uk every time I get a promo code, it doesn’t work? Every single time it says ‘no eligible stores’. I’ve tried on multiple devices, tried different addresses. Nothing! Please help, it’s beyond frustrating. https://t.co/6cqcRefWXY",
            {
                "entities": []
            }
        ],
        [
            "Voici une réduction de 5 € pour Uber Eats, valable sur la première commande (15 € minimum). Offre soumise à conditions. Code #UberEats à saisir au moment du paiement : eats-715fkx    https://t.co/nkIb4z9GzT…",
            {
                "entities": []
            }
        ],
        [
            "Code promo uber eats de -5€ sur votre première commande d’un montant de 15€: eats-14dkby6c0k",
            {
                "entities": []
            }
        ],
        [
            "@ubereats_fr Donne moi un code promo et je m'inscris",
            {
                "entities": []
            }
        ],
        [
            "@LEBELSylvie @DamienRieu @FrDesouche @ubereats_fr @Deliveroo_FR Les pages du code du travail doivent être fines comme du papier hygiénique...",
            {
                "entities": []
            }
        ],
        [
            "I made a grocery order on @UberEats yesterday from @sainsburys when received there was only 1 bag I didn’t take much notice when receiving and giving driver my code as the order has been delayed x 5 times and I was just glad he came by that point see part 2",
            {
                "entities": []
            }
        ],
        [
            "@ubereats_uk got a discount code through my email for 50% off just tried to order and it’s telling me no restaurant in my area gutted or what",
            {
                "entities": []
            }
        ],
        [
            "@DamienRieu @FrDesouche @ubereats_fr @Deliveroo_FR Code du travail en France 🇫🇷  « Nul ne peut, directement ou indirectement, embaucher, conserver à son service ou employer pour quelque durée que ce soit un étranger non muni du titre l'autorisant à exercer une activité salariée en France… » https://t.co/Mw3b82nTvg",
            {
                "entities": []
            }
        ],
        [
            "@DamienRieu @ubereats_fr @Deliveroo_FR Personnellement JAMAIS! Dès le début j’ai compris que l’Uberisation, un coup de Maclown qui a dû en avoir un retour sans doute(…!), était la création d’un statut d’esclave hors code du travail, qui permettait à des sans papiers de «travailler»en étant exploités! #STOPUberisation",
            {
                "entities": []
            }
        ],
        [
            "@DamienRieu @ubereats_fr @Deliveroo_FR À se demander pourquoi on respecte les lois, puisque, que ce soit en haut, ou en bas, ils se torchent avec le code du travail",
            {
                "entities": []
            }
        ],
        [
            "@ubereats_fr Code promo svp",
            {
                "entities": []
            }
        ],
        [
            "@ubereats_fr On veut un code promo 😉",
            {
                "entities": []
            }
        ],
        [
            "60% OFF Uber Eats! 🍔   Use Code: HAVINGANOLDFRIENDFORDINNER https://t.co/KJR6c7k6bS",
            {
                "entities": [
                    [
                        34,
                        60,
                        "CODE"
                    ]
                ]
            }
        ]
    ]
}